astrokit/__init__.py
astrokit/casa/__init__.py
astrokit/image/__init__.py
astrokit/image/fits.py
astrokit/image/noise.py
astrokit/oskar/Oskar.py
astrokit/oskar/__init__.py
astrokit/rascil/__init__.py
astrokit/utils/__init__.py
astrokit/utils/data.py
astrokit/utils/normalize.py
astrokit/utils/utils.py
astrokit/utils/scripts/__init__.py
astrokit/utils/scripts/fits2skymodel.py
astronomy_kit-0.0.5.dist-info/LICENSE
astronomy_kit-0.0.5.dist-info/METADATA
astronomy_kit-0.0.5.dist-info/WHEEL
astronomy_kit-0.0.5.dist-info/top_level.txt
astronomy_kit-0.0.5.dist-info/RECORD
