Metadata-Version: 2.1
Name: astronomy-kit
Version: 0.0.5
Summary: astronomy image processing kit
Author-email: Zhenhai CHEN <chenzhtbb@163.com>
Project-URL: Homepage, https://github.com/chenzhtbb/astrokit
Project-URL: Bug Tracker, https://github.com/chenzhtbb/astrokit/issues
Classifier: Programming Language :: Python :: 3
Classifier: License :: OSI Approved :: MIT License
Classifier: Operating System :: OS Independent
Requires-Python: >=3.10
License-File: LICENSE
Requires-Dist: wget
Requires-Dist: requests
Requires-Dist: numpy
Requires-Dist: scikit-image
